quicktransfer/__init__.py
quicktransfer/transfer.py
armaan_transfer-0.1.0.dist-info/METADATA
armaan_transfer-0.1.0.dist-info/WHEEL
armaan_transfer-0.1.0.dist-info/entry_points.txt
armaan_transfer-0.1.0.dist-info/top_level.txt
armaan_transfer-0.1.0.dist-info/RECORD
