Metadata-Version: 2.2
Name: armaan-transfer
Version: 0.1.0
Requires-Dist: tqdm
Dynamic: requires-dist
